archive-images/__init__.py
archive-images/archive_images.py
archiveImages/__init__.py
archiveImages/archive_images.py
archiveimages/__init__.py
archiveimages/archiveimages.py
archive_images-1.0.4.dist-info/METADATA
archive_images-1.0.4.dist-info/WHEEL
archive_images-1.0.4.dist-info/entry_points.txt
archive_images-1.0.4.dist-info/top_level.txt
archive_images-1.0.4.dist-info/RECORD
