Metadata-Version: 2.1
Name: archive-images
Version: 1.0.4
Summary: Archive images based on exif timestamp.
Home-page: https://github.com/pglira/archive-images
Author: Philipp Glira
Author-email: philipp.glira@gmail.com
License: MIT
Platform: UNKNOWN
Classifier: License :: OSI Approved :: MIT License
Classifier: Programming Language :: Python :: 3
Classifier: Programming Language :: Python :: 3.9
Requires-Dist: Pillow
